<profile>

<ReportVersion>
<Version>2019.2</Version>
</ReportVersion>

<UserAssignments>
<unit>ns</unit>
<ProductFamily>zynq</ProductFamily>
<Part>xc7z020-clg484-1</Part>
<TopModelName>Loop_BRAM_LOOP_proc1</TopModelName>
<TargetClockPeriod>11.10</TargetClockPeriod>
<ClockUncertainty>1.39</ClockUncertainty>
</UserAssignments>

<PerformanceEstimates>
<PipelineType>none</PipelineType>
<SummaryOfTimingAnalysis>
<unit>ns</unit>
<EstimatedClockPeriod>3.634</EstimatedClockPeriod>
</SummaryOfTimingAnalysis>
<SummaryOfOverallLatency>
<unit>clock cycles</unit>
<Best-caseLatency>25201</Best-caseLatency>
<Average-caseLatency>25201</Average-caseLatency>
<Worst-caseLatency>25201</Worst-caseLatency>
<Best-caseRealTimeLatency>0.280 ms</Best-caseRealTimeLatency>
<Average-caseRealTimeLatency>0.280 ms</Average-caseRealTimeLatency>
<Worst-caseRealTimeLatency>0.280 ms</Worst-caseRealTimeLatency>
<Interval-min>25201</Interval-min>
<Interval-max>25201</Interval-max>
</SummaryOfOverallLatency>
<SummaryOfLoopLatency>
<BRAM_LOOP>
<TripCount>3600</TripCount>
<Latency>25200</Latency>
<IterationLatency>7</IterationLatency>
<BRAM_LOOP.1>
<TripCount>4</TripCount>
<Latency>4</Latency>
<PipelineII>1</PipelineII>
<PipelineDepth>2</PipelineDepth>
</BRAM_LOOP.1>
</BRAM_LOOP>
</SummaryOfLoopLatency>
</PerformanceEstimates>

<AreaEstimates>
<Resources>
<FF>56</FF>
<LUT>135</LUT>
<BRAM_18K>0</BRAM_18K>
<DSP48E>0</DSP48E>
<URAM>0</URAM>
</Resources>
<AvailableResources>
<BRAM_18K>280</BRAM_18K>
<DSP48E>220</DSP48E>
<FF>106400</FF>
<LUT>53200</LUT>
<URAM>0</URAM>
</AvailableResources>
</AreaEstimates>

<InterfaceSummary>
<RtlPorts>
<name>ap_clk</name>
<Object>Loop_BRAM_LOOP_proc1</Object>
<Type>return value</Type>
<Scope></Scope>
<IOProtocol>ap_ctrl_hs</IOProtocol>
<IOConfig></IOConfig>
<Dir>in</Dir>
<Bits>1</Bits>
<Attribute>control</Attribute>
</RtlPorts>
<RtlPorts>
<name>ap_rst</name>
<Object>Loop_BRAM_LOOP_proc1</Object>
<Type>return value</Type>
<Scope></Scope>
<IOProtocol>ap_ctrl_hs</IOProtocol>
<IOConfig></IOConfig>
<Dir>in</Dir>
<Bits>1</Bits>
<Attribute>control</Attribute>
</RtlPorts>
<RtlPorts>
<name>ap_start</name>
<Object>Loop_BRAM_LOOP_proc1</Object>
<Type>return value</Type>
<Scope></Scope>
<IOProtocol>ap_ctrl_hs</IOProtocol>
<IOConfig></IOConfig>
<Dir>in</Dir>
<Bits>1</Bits>
<Attribute>control</Attribute>
</RtlPorts>
<RtlPorts>
<name>ap_done</name>
<Object>Loop_BRAM_LOOP_proc1</Object>
<Type>return value</Type>
<Scope></Scope>
<IOProtocol>ap_ctrl_hs</IOProtocol>
<IOConfig></IOConfig>
<Dir>out</Dir>
<Bits>1</Bits>
<Attribute>control</Attribute>
</RtlPorts>
<RtlPorts>
<name>ap_continue</name>
<Object>Loop_BRAM_LOOP_proc1</Object>
<Type>return value</Type>
<Scope></Scope>
<IOProtocol>ap_ctrl_hs</IOProtocol>
<IOConfig></IOConfig>
<Dir>in</Dir>
<Bits>1</Bits>
<Attribute>control</Attribute>
</RtlPorts>
<RtlPorts>
<name>ap_idle</name>
<Object>Loop_BRAM_LOOP_proc1</Object>
<Type>return value</Type>
<Scope></Scope>
<IOProtocol>ap_ctrl_hs</IOProtocol>
<IOConfig></IOConfig>
<Dir>out</Dir>
<Bits>1</Bits>
<Attribute>control</Attribute>
</RtlPorts>
<RtlPorts>
<name>ap_ready</name>
<Object>Loop_BRAM_LOOP_proc1</Object>
<Type>return value</Type>
<Scope></Scope>
<IOProtocol>ap_ctrl_hs</IOProtocol>
<IOConfig></IOConfig>
<Dir>out</Dir>
<Bits>1</Bits>
<Attribute>control</Attribute>
</RtlPorts>
<RtlPorts>
<name>buffer_V_Addr_A</name>
<Object>buffer_V</Object>
<Type>array</Type>
<Scope></Scope>
<IOProtocol>bram</IOProtocol>
<IOConfig></IOConfig>
<Dir>out</Dir>
<Bits>32</Bits>
<Attribute>address</Attribute>
</RtlPorts>
<RtlPorts>
<name>buffer_V_EN_A</name>
<Object>buffer_V</Object>
<Type>array</Type>
<Scope></Scope>
<IOProtocol>bram</IOProtocol>
<IOConfig></IOConfig>
<Dir>out</Dir>
<Bits>1</Bits>
<Attribute>control</Attribute>
</RtlPorts>
<RtlPorts>
<name>buffer_V_WEN_A</name>
<Object>buffer_V</Object>
<Type>array</Type>
<Scope></Scope>
<IOProtocol>bram</IOProtocol>
<IOConfig></IOConfig>
<Dir>out</Dir>
<Bits>4</Bits>
<Attribute>control</Attribute>
</RtlPorts>
<RtlPorts>
<name>buffer_V_Din_A</name>
<Object>buffer_V</Object>
<Type>array</Type>
<Scope></Scope>
<IOProtocol>bram</IOProtocol>
<IOConfig></IOConfig>
<Dir>out</Dir>
<Bits>32</Bits>
<Attribute>data</Attribute>
</RtlPorts>
<RtlPorts>
<name>buffer_V_Dout_A</name>
<Object>buffer_V</Object>
<Type>array</Type>
<Scope></Scope>
<IOProtocol>bram</IOProtocol>
<IOConfig></IOConfig>
<Dir>in</Dir>
<Bits>32</Bits>
<Attribute>data</Attribute>
</RtlPorts>
<RtlPorts>
<name>gray_plate_data_stream_0_V_dout</name>
<Object>gray_plate_data_stream_0_V</Object>
<Type>pointer</Type>
<Scope></Scope>
<IOProtocol>ap_fifo</IOProtocol>
<IOConfig></IOConfig>
<Dir>in</Dir>
<Bits>8</Bits>
<Attribute>control</Attribute>
</RtlPorts>
<RtlPorts>
<name>gray_plate_data_stream_0_V_empty_n</name>
<Object>gray_plate_data_stream_0_V</Object>
<Type>pointer</Type>
<Scope></Scope>
<IOProtocol>ap_fifo</IOProtocol>
<IOConfig></IOConfig>
<Dir>in</Dir>
<Bits>1</Bits>
<Attribute>control</Attribute>
</RtlPorts>
<RtlPorts>
<name>gray_plate_data_stream_0_V_read</name>
<Object>gray_plate_data_stream_0_V</Object>
<Type>pointer</Type>
<Scope></Scope>
<IOProtocol>ap_fifo</IOProtocol>
<IOConfig></IOConfig>
<Dir>out</Dir>
<Bits>1</Bits>
<Attribute>control</Attribute>
</RtlPorts>
</InterfaceSummary>

</profile>
